{"id":"160002254072","nome":"IVO DA SAÚDE","partido":"PSDB","municipio":"MANGUEIRINHA","uf":"PR","text":"[INFRAESTRUTURA]\n…pedra britanas principais vias dointerior;\n Implantar o“PROGRAMACAMINHOS DOCAMPO” -Realizar asfalto nas principais\nestradas rurais;\n Implantar o “PROGRAMA CALCAMENTO RURAL” - Executar calcamento no\ninteriordoMunicípio, priorizando as e…\n\n---\n\n[TURISMO]\n…00% gratuito para aqueles que\nestudam nos municípios de Pato Branco e Palmas bem como ampliando os locais de\nembarque edesembarque;\n Abertura de EscolaTécnica Profissionalizante;\nCULTURAETURISMO–MANGUEIRINHAEARTE\n CriaçãodaSecretaria d…\n\n---\n\n[ASSISTÊNCIA SOCIAL]\n…ABITAÇÃO -DIGNIDADE DE UMLARAS FAMILIASCARENTES\n Realizar o maior programa Habitacional de Mangueirinha, 200 casas – “CASA\nSOCIALELOTE SOCIAL”;\nPROGRAMADE ENFRENTAMENTOAVULNERABILIDADE\n Retirar as famílias que estão vivendo em situa…\n\n---\n\n[TRANSPORTE E MOBILIDADE]\n…icipais (assessoria jurídica, administrativo e\ncontábil)valorizando ocontrole social;\n Estudo de viabilização de implantação do Programa de transporte coletivo municipal -\nTRANSCIDADÃO(bairros/centros e parqueindustriais);\n Implantar o “P…\n\n---\n\n[IDOSO]\n…m de Mangueirinha (Parceriacom comércio local para descontos);\n Cursos relacionados a vida adulta (educação financeira, como declarar IR, como abrir\numaempresa etc.);\nNUCLEODATERCEIRAIDADE\n Construção de um espaço para atendimento di…\n\n---\n\n[SAÚDE MENTAL]\n…antar o “PROGRAMA MAMA MIA” - Ampliação de exames para prevenção de\ncâncer deMAMA;\n Implantar o Centro de Especialidade Odontológica - CEO, oferecer tratamento de canal\ne atendimento a pacientes especiais (alunos da APAE entre outros) no pró…\n\n---\n\n[TRANSPARÊNCIA E ÉTICA]\n…tivas – em diversas modalidades,\ncontemplando faixas etárias diferenciadas, envolvendo a comunidade em vários\nperíodos doano (cidade eInterior);\n Construção de um parque com Lagos, pista de caminhada, quadras sintéticas, parque\ninfant…\n\n---\n\n[HABITAÇÃO]\n…rnet gratuitaem locais deatendimento ao cidadão;\n Ampliararede deesgoto para 100%da area urbana em parceria com aSANEPAR;\n Viabilizar o aumento do efetivo das policias Civil e Militar junto ao Governo do Estado\ndoParaná;\n Incentivare ap…\n\n---\n\n[GESTÃO PÚBLICA]\n…Plano de Governo\n“GESTÃO NOVA, FUTURO PROMISSOR”\nIvo da Saúde\nAproposta de governo é em favor de uma administração pública organizada, voltada para a\nvalorização e capacitaç…\n\n---\n\n[COMBATE ÀS DROGAS]\n…jurídico);\n Projeto de APOIO AOS PAIS - Orientação educação sócio - familiar e mediação de\nconflitos;\n Resgatede valores morais esociais, solidariedade e respeito intrafamiliar (pais e filhos);\n Ações deprevençãoaviolência, alcoolis…\n\n---\n\n[AGRICULTURA E RURAL]\n…LICIANO LEONARCHIK\n–IVODASAÚDE EDOVICEADELARDEONPARAAGESTAO2025A2028.\nAGROPECUÁRIA,AGRICULTURAFAMILIARE OAGRONEGÓCIO\n Tornar Mangueirinha referência na Bacia Leiteira do Sudoeste - PR, (qualificação,\nassistência técnica, auxílio com equipam…\n\n---\n\n[EDUCAÇÃO]\n…em áreas públicas;\n Potencializar e promover caminhadas ecológicas com intuito educacional em parceria\ncom a Secretaria de Educação, Esporte e Saúde, para que o cidadão conheça suas\nbelezas naturais e alerte aestes o interessea preserva…\n\n---\n\n[EMPREGO E RENDA]\n…oIguaçu);\nINDÚSTRIACOMÉRCIO E SERVICOS–MANGUEIRINHAPODE MAIS\n Estruturaa novaarea industrial;\n TornarMangueirinha centro regional denegócios - industria, comercio e serviços;\n Criar o “PROGRAMA MUNICIPAL MEU PRIMEIRO EMPREGO PARA OS\nJ…\n\n---\n\n[TECNOLOGIA E INOVAÇÃO]\n…O DE PRODUTOR) com\nplantãonoperíododasafra;\n Implantar o “PROGRAMA CONEXAO DE INTERNET NO MEIO RURAL” –\ntecnologiamais próximadoprodutor;\n Implantaro“PROGRAMAde QUALIFICACAO DOJOVEM noCAMPO”;\n Incentivar a Implantação de AGRO INDÚSTRIAS…\n\n---\n\n[SAÚDE]\n…Plano de Governo\n“GESTÃO NOVA, FUTURO PROMISSOR”\nIvo da Saúde\nAproposta de governo é em favor de uma administração pública organizada, voltada para a\nvalorização e capacitação das pessoas, com respeito pelo ci…\n\n---\n\n[POVOS INDÍGENAS]\n…rupodoCTGecomunidades dointerior;\n Implantaçãodo CINEMANG –nas instalações docentro de eventos, com apresentações\nmensais;\n Implantar nas escolas o PROJETO CULTURAL DE ETNIAS (ITALIANO, ALEMÃO\nINDIGENA) entre outros quecompõem oMUNICÍPI…\n\n---\n\n[SANEAMENTO BÁSICO]\n…NA\nCOMUNIDADE”- aproximandoa populaçãodaadministraçãomunicipal;\n Criar o cadastro único do cidadão visando acompanhar os serviços utilizados por cada\ncidadãonas ações desaúdepública;\n Oferecer sinalpúblico deinternet gratuitaem locai…\n\n---\n\n[PESSOA COM DEFICIÊNCIA]\n…inhaindustrial,equipamentos detecnologia, conjuntos escolares);\n Capacitar profissionais para atender todas as crianças com transtorno de aprendizado\nglobal,TEAeoutras deficiências;\n Construçãoda novaSededa EscolaAndré Dorini;\n Programa q…\n\n---\n\n[CRIANÇA E ADOLESCENTE]\n…as necessidades de cada escola e CMEI (utensílios de\ncozinhaindustrial,equipamentos detecnologia, conjuntos escolares);\n Capacitar profissionais para atender todas as crianças com transtorno de aprendizado\nglobal,TEAeoutras deficiência…\n\n---\n\n[MEIO AMBIENTE]\n…unicípio, promovendo o desenvolvimento, sustentado no equilíbrio\nsocioeconômico e ambiental. Queremos mediante esse plano de trabalho apresentar as\npropostas que de forma participativa, em conjunto com as entidades da comunidade foram\nelei…\n\n---\n\n[SEGURANÇA ALIMENTAR]\n…s;\n OFICINAS eGINCANAS deprevençãoas drogas e aviolência;\n Semanade jogos da juventude(dos 15aos 29anos conforme Estatuto daJuventude);\n Parcerias Público Privadapara incentivo decontrataçãodejovens;\n Incentivar a criação do Progr…\n\n---\n\n[MULHER]\n…s esociais, solidariedade e respeito intrafamiliar (pais e filhos);\n Ações deprevençãoaviolência, alcoolismo edrogas;\n Acesso aos direitos einclusões sociais;\n Criaçãodenúcleos de referência com equipes especilizadas;\nCRIAÇÃO DO NÚCL…\n\n---\n\n[REGULARIZAÇÃO FUNDIÁRIA]\n…to no\ninteriordoMunicípio, priorizando as estradas de maiorfluxo eserras;\n Implantar o “PROGRAMA PROPRIEDADE LEGAL” - Liberações ambientais, CAR,\nCAD-PROCCIR, ITR,entre outros;\n Ampliar o PROGRAMA DE REFORMA E CONSTRUCAO DE CASAS PARA\nAGRI…\n\n---\n\n[CULTURA, ESPORTE E LAZER]\n…ANO LEONARCHIK\n–IVODASAÚDE EDOVICEADELARDEONPARAAGESTAO2025A2028.\nAGROPECUÁRIA,AGRICULTURAFAMILIARE OAGRONEGÓCIO\n Tornar Mangueirinha referência na Bacia Leiteira do Sudoeste - PR, (qualificação,\nassistência técnica, auxílio com equipam…\n\n---\n\n[FINANÇAS PÚBLICAS]\n…o, Esporte e Saúde, para que o cidadão conheça suas\nbelezas naturais e alerte aestes o interessea preservação;\nADMINISTRAÇÃO,FINANÇASE URBANISMO\n Coordenar oPlanejamento Geral doMunicípio (Plano Diretor);\n Discutir e alterar em parceria…\n\n---\n\n[ENERGIA E ILUMINAÇÃO]\n…Proteção Animal que vise a fiscalização, por parte do poder\npúblico, demaus-tratos noMunicípiode Mangueirinha;\n Promover a mobilidade sustentável criando ciclovias e ciclo faixas para incentivar o uso\ndebicicletas;\n Reduzir o consu…\n\n---\n\n[SEGURANÇA PÚBLICA]\n…m sede própria e\nveículo adequado;\n Implantar o “PROGRAMA DE MELHORIA AS CALÇADAS E PASSEIOS”\npermitindo otráfego depedestres com segurança;\n Ampliação e melhoria no sistema de gerenciamento de coleta de lixo com a\nreformulaçãodosistemad…","themes":["transporte e mobilidade","turismo","saúde mental","saúde","cultura, esporte e lazer","criança e adolescente","educação","transparência e ética","energia e iluminação","segurança pública","habitação","assistência social","regularização fundiária","povos indígenas","emprego e renda","pessoa com deficiência","infraestrutura","saneamento básico","segurança alimentar","finanças públicas","gestão pública","tecnologia e inovação","meio ambiente","agricultura e rural","idoso","combate às drogas","mulher"]}