{"id":"160002172907","nome":"SILVIO VALOSKI","partido":"PRTB","municipio":"TIJUCAS DO SUL","uf":"PR","text":"[INFRAESTRUTURA]\n…mental.\n1\nINDÚSTRIA E COMÉRCIO\n• Criação do Parque Industrial: Preparar área com energia elétrica, asfalto e liberações\npertinentes destinada a atrair empresas e indústrias para nossa Cidade. Esta ação visa\naumentar a geração de empregos…\n\n---\n\n[TURISMO]\n…ino.\n• Ampliação da coleta de lixo em todo município.\n• Instalação de lixeiras comunitárias para facilitar a coleta de lixo.\nTURISMO.\n• Programa prato típico tijuquense: Fomentar ações para que possamos criar o prato\ntípico da nossa cida…\n\n---\n\n[ASSISTÊNCIA SOCIAL]\n…icipal de Ensino.\n• Buscar a efetivação gradativa da implantação do Projeto de Educação Integral nas\nunidades escolares e promover parceria com a Secretaria de Assistência Social, Cultura\ne Esporte.\n• Buscar convênio com o Governo Estadual e Federa…\n\n---\n\n[TRANSPORTE E MOBILIDADE]\n…cimento de lanche aos pacientes que necessitam de\nconsultas fora do município e que utilizam o transporte sanitário.\n• Ampliar horário de atendimento nas unidades de saúde nas localidades da Campina,\nCentro e Fagundes ates às 19 horas.\n• Au…\n\n---\n\n[IDOSO]\n…grama envelhecimento ativo: Criar iniciativas para promover a saúde e o\nbem-estar dos idosos, incluindo atividades físicas, workshops de saúde e suporte social.\n• Programa Educação em Saúde destinado aos nossos Agricultores.\n• Melhorar…\n\n---\n\n[SAÚDE MENTAL]\n…horas.\n• Aumento do número de profissionais efetivos de odontologia\n• Reestruturar o Programa de Saúde Mental com foco em prestar acolhimento e\nacompanhamento aos pacientes de forma respeitosa e empática, promovendo a\nprevenção e a promoção…\n\n---\n\n[TRANSPARÊNCIA E ÉTICA]\n…fruticultura com doação de mudas.\n• Apoio para facilitar a retirada de guia para transporte animal.\n• Cadastramento via secretaria de agricultura do rebanho animal do Município com\nfinalidade de melhoria genética do rebanho\n• Programa…\n\n---\n\n[HABITAÇÃO]\n…romovendo\natividades nas escolas Municipais e Estaduais.\nSOCIAL\n• Reativar o funcionamento do Núcleo Ceia de segunda a sexta-feira.\n• Programa moradia social: Construção de casas para moradores em área de risco\n• Ampliação da casa de ido…\n\n---\n\n[GESTÃO PÚBLICA]\n…PROGRAMA DE GOVERNO\nGESTÃO 2025/2028\nSILVIO VALOSKI e OLDAIR DA VAINET\nSAÚDE\n• Realizar estudos de viabilidade técnica e financeira para construção de um novo hospital\nem Tijuc…\n\n---\n\n[COMBATE ÀS DROGAS]\n…abalho para 30 horas dos\nprofissionais da saúde.\n• Criar programa de trabalho preventivo para tratamento da drogadição, alcoolismo e\noutras enfermidades.\n• Programa lanche solidário: Fornecimento de lanche aos pacientes que necessitam de\nco…\n\n---\n\n[AGRICULTURA E RURAL]\n…s).\n• Fornecimento da alimentação escolar com elaboração de cardápio diversificado e\nacompanhado pela nutricionista, com a aquisição de produtos fornecidos pelo Programa\nda Agricultura Familiar.\n• Garantir os princípios da Gestão Democrática…\n\n---\n\n[EDUCAÇÃO]\n…idosos, incluindo atividades físicas, workshops de saúde e suporte social.\n• Programa Educação em Saúde destinado aos nossos Agricultores.\n• Melhorar a saúde e o bem-estar da população de Tijucas do Sul com investimentos e\nmelhorias estr…\n\n---\n\n[EMPREGO E RENDA]\n…s destinada a atrair empresas e indústrias para nossa Cidade. Esta ação visa\naumentar a geração de empregos em nosso Município.\n• Criação da Nota Tijucana, com sorteios de prêmios a quem comprar no comércio local.\n• Projeto para Construç…\n\n---\n\n[TECNOLOGIA E INOVAÇÃO]\n…ade de agricultores.\n• Convenio com órgãos Estaduais com a finalidade de proporcionar mais cursos para todos\nos agricultores.\n• Festa do agricultor, voltada ao agricultor, onde haverá exposição de novas tecnologias,\nanimais e outras atraçõe…\n\n---\n\n[SAÚDE]\n…PROGRAMA DE GOVERNO\nGESTÃO 2025/2028\nSILVIO VALOSKI e OLDAIR DA VAINET\nSAÚDE\n• Realizar estudos de viabilidade técnica e financeira para construção de um novo hospital\nem Tijucas do Sul em parceria com o Governo do Estado.\n• C…\n\n---\n\n[SANEAMENTO BÁSICO]\n…rio\ncentral não tem mais lotes a serem utilizados.\n• Ampliação da educação ambiental em toda rede de ensino.\n• Ampliação da coleta de lixo em todo município.\n• Instalação de lixeiras comunitárias para facilitar a coleta de lixo.\nTURISMO.\n• Prog…\n\n---\n\n[PESSOA COM DEFICIÊNCIA]\n…strativa com a redução de cargos comissionados.\n7\n• Aquisição de equipamentos para defesa civil\n• Ampliação e melhoria no atendimento dos serviços da Copel, Sanepar e Correios.\n• Projeto para revitalização de toda rua XV de Novembro, melhorando…\n\n---\n\n[CRIANÇA E ADOLESCENTE]\n…Programa moradia social: Construção de casas para moradores em área de risco\n• Ampliação da casa de idosos\n• Ampliação da casa de acolhimento a crianças.\n• Programa para reativar e incentivar a realização de diversos cursos, como corte,…\n\n---\n\n[MEIO AMBIENTE]\n…cal.\n• Incentivar e apoiar o modelo associativista e cooperativo para a venda dos produtos aqui\nproduzidos.\nMEIO AMBIENTE\n• Criação da Diretoria do Bem-estar Animal: A diretoria irá contar com profissional\nveterinário para desenvolver programa…\n\n---\n\n[SEGURANÇA ALIMENTAR]\n…unicípio.\n• Instalação de lixeiras comunitárias para facilitar a coleta de lixo.\nTURISMO.\n• Programa prato típico tijuquense: Fomentar ações para que possamos criar o prato\ntípico da nossa cidade, ajudando assim a divulgar o Município…\n\n---\n\n[REGULARIZAÇÃO FUNDIÁRIA]\n…s.\n• Aquisição de britador móvel para melhorar a recuperação das estradas rurais.\n• Criação de comitê envolvendo a secretaria de Urbanismo e área jurídica do Município\npara agilizar e melhorar o andamento dos processos de regularização fundiária.\n• Gara…\n\n---\n\n[CULTURA, ESPORTE E LAZER]\n…m programas do Governo\ndo Estado.\n• Parque de eventos: Projeto para construir parque destinado a grandes eventos em local\napropriado.\nCULTURA\n• Estudo para reativar e incentivar peças de teatro no Município.\n• Festa de Natal: Incentivar…\n\n---\n\n[FINANÇAS PÚBLICAS]\n…dadãos do Município.\n• Estudo de impacto financeiro para pagamento do piso salarial aos profissionais de\nenfermagem.\n• Estudar o impacto financeiro da redução da carga de trabalho para 30 horas dos\nprofissionais da saúde.\n• Criar pro…\n\n---\n\n[ENERGIA E ILUMINAÇÃO]\n…inalidade\nde proporcionar treinamento e qualificação constantes dos nossos trabalhadores.\n• Projeto para Iluminação Pública da Campina até a região da Lagoa.\n• Implantar curso de capacitação para que os comerciantes locais possam participar das\nlic…\n\n---\n\n[SEGURANÇA PÚBLICA]\n…a, material de expediente e de consumo, para\nmanutenção das instituições de ensino e secretaria municipal de educação.\n• Assegurar a efetivação de medidas de segurança e bem-estar dos alunos, no trajeto que\nestes percorrem no ônibus escola…","themes":["transporte e mobilidade","turismo","saúde mental","saúde","cultura, esporte e lazer","criança e adolescente","educação","transparência e ética","energia e iluminação","segurança pública","habitação","assistência social","regularização fundiária","emprego e renda","pessoa com deficiência","infraestrutura","saneamento básico","segurança alimentar","finanças públicas","gestão pública","tecnologia e inovação","meio ambiente","agricultura e rural","idoso","combate às drogas"]}