{"id":"170002257848","nome":"CELINA BRITO","partido":"REPUBLICANOS","municipio":"JUPI","uf":"PE","text":"[INFRAESTRUTURA]\n…, educação, administração, desenvolvimento econômico, cultura,\ndesporto, turismo, infraestrutura, assistência social e meio ambiente.\nEnfrentaremos com humildade, compromisso, entusiasmo e respeito, as\nresponsabilidades que estão por vir. Por i…\n\n---\n\n[TURISMO]\n…ra, saúde, educação, administração, desenvolvimento econômico, cultura,\ndesporto, turismo, infraestrutura, assistência social e meio ambiente.\nEnfrentaremos com humildade, compromisso, entusiasmo e respeito, as\nresponsabilidades que estã…\n\n---\n\n[ASSISTÊNCIA SOCIAL]\n…nistração, desenvolvimento econômico, cultura,\ndesporto, turismo, infraestrutura, assistência social e meio ambiente.\nEnfrentaremos com humildade, compromisso, entusiasmo e respeito, as\nresponsabilidades que estão por vir. Por isso, valorizaremos a…\n\n---\n\n[TRANSPORTE E MOBILIDADE]\n…madrugada e manutenção da casa de apoio de Recife;\n- Disponibilização de carro para transporte dos pacientes e acompanhantes da Casa De\nApoio de Recife aos respectivos hospitais da capital;\n- Disponibilização de veículos nas Comunidades par…\n\n---\n\n[IDOSO]\n…vir. Por isso, valorizaremos a força da mulher, dos\njovens, dos agricultores, dos idosos e de cada cidadão jupiense.\nO Plano de Governo aqui apresentado representa um modelo de gestão com\nparticipação cidadã, pois Jupi é do seu povo!\nI…\n\n---\n\n[SAÚDE MENTAL]\n…os os funcionários para o devido acolhimento\nàs pessoas;\n- Pleitear a implantação do CAP’S (Centro de Assistência Psicossocial);\n- Aquisição de Aparelhos para exames especializados;\n- Aquisição de marcas extras para o Hospital Municip…\n\n---\n\n[TRANSPARÊNCIA E ÉTICA]\n…lização do site da prefeitura, com publicações de diário oficial, a fim de que haja\nde fato, transparência para com a população;\n- Disponibilizar veículos para transportar a população do espaço rural para a sede do\nMunicípio no dia da feira li…\n\n---\n\n[HABITAÇÃO]\n…ivação dos auxílios assistenciais;\n- Criação do plano de erradicação de residências sem condições de moradia;\n- Criar espaços que potencializem a participação ativa dos jovens nas decisões políticas\nlocais;\n- Revisão do Cadastro Único pa…\n\n---\n\n[GESTÃO PÚBLICA]\n…PLANO DE GOVERNO PARA GESTÃO MUNICIPAL, 2025 A 2028\n“Jupi abraça o seu povo”\nCandidata a Prefeita: Celina Tenório de Brito Maciel\nCandidato a Vice Prefeito: Jair Monteiro Freitas…\n\n---\n\n[COMBATE ÀS DROGAS]\n…ntes;\n- Assegurar ações através de campanhas educativas e de sensibilização para prevenção ao\nuso de drogas e dependência química, fortalecendo a rede de serviços;\n- Estender e descentralizar a Assistência Social até a zona rural, nos q…\n\n---\n\n[AGRICULTURA E RURAL]\n…tão\nverdadeiramente comprometida com a população em todas as searas, quais sejam:\nagricultura, saúde, educação, administração, desenvolvimento econômico, cultura,\ndesporto, turismo, infraestrutura, assistência social e meio ambiente.\nEnfrent…\n\n---\n\n[EDUCAÇÃO]\n…comprometida com a população em todas as searas, quais sejam:\nagricultura, saúde, educação, administração, desenvolvimento econômico, cultura,\ndesporto, turismo, infraestrutura, assistência social e meio ambiente.\nEnfrentaremos com humild…\n\n---\n\n[EMPREGO E RENDA]\n…onalizantes destinados aos pais de pessoas portadoras de\ndeficiências;\n- Desenvolver oficinas de trabalhos manuais, tais como: bordado, crochê, tricô, pinturas,\ndentre outras, destinadas as crianças e jovens;\n- Criação de mirantes, explor…\n\n---\n\n[TECNOLOGIA E INOVAÇÃO]\n…V- DESENVOLVIMENTO ECONÔMICO:\n- Criar legislação municipal de apoio às empresas geradoras de tecnologias e inovação,\nque utilizam energias alternativas e desenvolvem processos produtivos ambientalmente\nsustentáveis;\n- Criar o Programa Jupi…\n\n---\n\n[SAÚDE]\n…amente comprometida com a população em todas as searas, quais sejam:\nagricultura, saúde, educação, administração, desenvolvimento econômico, cultura,\ndesporto, turismo, infraestrutura, assistência social e meio ambiente.\nEnfrentaremos…\n\n---\n\n[LGBTQIA+]\n…ticas públicas que visem a\npromoção dos direitos de pessoas negras, jovens, pessoas com deficiência,\nLGBTQIAPN+, além de combater a violência contra a mulher;\n- Garantir políticas e práticas de não discriminação;\n- Reativação dos auxílio…\n\n---\n\n[SANEAMENTO BÁSICO]\n…’Água e Casas Populares;\n- Construção de rampas de acessibilidade.\n- Aplicação do Plano Municipal de Saneamento Básico;\n- Realização do georreferenciamento dos bairros em parceria com os órgãos públicos\ncompetentes;\n- Conservação da estrutu…\n\n---\n\n[PESSOA COM DEFICIÊNCIA]\n…mbros da família e de forma especial às crianças;\n- Criação do Conselho da Pessoa com Deficiência;\n- Aquisição da Motolância do SAMU;\n- Aquisição de ambulâncias de porte grande;\n- Disponibilizar profissionais de educação física para gratuita…\n\n---\n\n[CRIANÇA E ADOLESCENTE]\n…ará o apoio tanto\nàs mães quanto aos demais membros da família e de forma especial às crianças;\n- Criação do Conselho da Pessoa com Deficiência;\n- Aquisição da Motolância do SAMU;\n- Aquisição de ambulâncias de porte grande;\n- Disponibili…\n\n---\n\n[MEIO AMBIENTE]\n…mento econômico, cultura,\ndesporto, turismo, infraestrutura, assistência social e meio ambiente.\nEnfrentaremos com humildade, compromisso, entusiasmo e respeito, as\nresponsabilidades que estão por vir. Por isso, valorizaremos a força da mulher…\n\n---\n\n[SEGURANÇA ALIMENTAR]\n…de alcoolismo e uso de drogas;\n- Criar programas de combate ao frio e a fome;\n- Avançar no combate a insegurança alimentar com o atendimento de famílias em situação\nde vulnerabilidade social;\n- Integralizar as Secretarias de Saúde e Assistência Soci…\n\n---\n\n[MULHER]\n…peito, as\nresponsabilidades que estão por vir. Por isso, valorizaremos a força da mulher, dos\njovens, dos agricultores, dos idosos e de cada cidadão jupiense.\nO Plano de Governo aqui apresentado representa um modelo de gestão com\npartic…\n\n---\n\n[CULTURA, ESPORTE E LAZER]\n…verdadeiramente comprometida com a população em todas as searas, quais sejam:\nagricultura, saúde, educação, administração, desenvolvimento econômico, cultura,\ndesporto, turismo, infraestrutura, assistência social e meio ambiente.\nEnfrent…\n\n---\n\n[FINANÇAS PÚBLICAS]\n…strutura, assistência social e meio ambiente.\nEnfrentaremos com humildade, compromisso, entusiasmo e respeito, as\nresponsabilidades que estão por vir. Por isso, valorizaremos a força da mulher, dos\njovens, dos agricultores, dos idoso…\n\n---\n\n[ENERGIA E ILUMINAÇÃO]\n…e desenvolvendo\no comércio local;\n- Substituir as lâmpadas das vias públicas por lâmpadas de led, proporcionando maior\nsegurança à população;\n- Iluminação das margens da BR;\n- Elaboração do Plano de Cargos e Carreiras para os servido…\n\n---\n\n[SEGURANÇA PÚBLICA]\n…s para\ncuidar da saúde animal e fazer castrações gratuitas;\n- Criação do Departamento de Segurança Municipal, onde haverá discussão com a\nsociedade para criação da Guarda Municipal de Jupi-PE;\n- ⁠Realizar a instalação de câmeras em toda a…","themes":["transporte e mobilidade","turismo","saúde mental","saúde","LGBTQIA+","cultura, esporte e lazer","criança e adolescente","educação","transparência e ética","energia e iluminação","segurança pública","habitação","assistência social","emprego e renda","pessoa com deficiência","infraestrutura","saneamento básico","segurança alimentar","finanças públicas","gestão pública","tecnologia e inovação","meio ambiente","agricultura e rural","idoso","combate às drogas","mulher"]}