{"id":"190002257703","nome":"DAVI SOUZA","partido":"REDE","municipio":"MAGÉ","uf":"RJ","text":"[INFRAESTRUTURA]\n…garantindo melhores condições\nde trabalho e incentivos para desenvolvimento profissional.\n● Infraestrutura Escolar: Modernizar e ampliar as escolas municipais, garantindo que\ntodas as unidades tenham laboratórios de informática, bibliotecas at…\n\n---\n\n[TURISMO]\n…tos culturais que\nenvolva todas as comunidades da cidade, promovendo a valorização da cultura local\ne o turismo.\n● Esporte para Todos: Ampliar a oferta de atividades esportivas em todos os bairros,\ncom a construção de quadras poliesporti…\n\n---\n\n[ASSISTÊNCIA SOCIAL]\n…gramas de mentorias para os estudantes do ensino médio, preparando-os para o\nmercado de trabalho.\nAssistência Social: A assistência social deve ser um pilar para a redução das\ndesigualdades e promoção da inclusão social. Propostas incluem:\n● Fortal…\n\n---\n\n[TRANSPORTE E MOBILIDADE]\n…stria e comércio. E combater a\ndesigualdade entre homens e mulheres no serviço público.\n● Transporte - Criar a Empresa publica de transportes encerrando a dependência de\nempresas sem compromisso público. Estabelecer regulamentar e oficializ…\n\n---\n\n[IDOSO]\n…o\npsicológico, jurídico e de encaminhamento para programas de capacitação\nprofissional.\n● Atenção ao Idoso: Criar Centros de Convivência do Idoso em cada distrito da\ncidade, oferecendo atividades culturais, recreativas e de lazer, além…\n\n---\n\n[SAÚDE MENTAL]\n…de consultas especializadas, exames e cirurgias,\nvisando zerar as filas de espera.\n● Saúde Mental: Criar centros de atendimento psicossocial em áreas estratégicas da\ncidade para oferecer suporte psicológico e psiquiátrico, com especial atençã…\n\n---\n\n[TRANSPARÊNCIA E ÉTICA]\n…no município conforme normas federais. E revisar qualquer\ncontrato relacionado a mesma.\n● Transparência - Garantir a democratização e acesso de todos os contratos de\nempresas que operam serviços fundamentais no município (como transporte públ…\n\n---\n\n[HABITAÇÃO]\n…dade já existente e atualmente sem\nuso, no hospital Dr Walter Arruda em Santo Aleixo.\n● Casa do autista - Buscar expertise de municípios que já contam com uma unidade\nvoltada a causa, na construção desse espaço referência em Magé.\n● M…\n\n---\n\n[GESTÃO PÚBLICA]\n…rios de entrada e saída, além de\nimplementar programas de segurança voltados para estudantes e professores.\n3. Gestão Ambiental Integrada\nA preservação ambiental é crucial para garantir a qualidade de vida das gerações futuras.\nProposta…\n\n---\n\n[COMBATE ÀS DROGAS]\n…histórico médico do paciente\nde forma rápida e segura, facilitando diagnósticos e tratamentos.\n● Telemedicina: Implementar serviços de telemedicina para consultas em áreas\nremotas ou para especialidades que possuem maior demanda, reduzindo…\n\n---\n\n[AGRICULTURA E RURAL]\n…o ecoturismo, turismo histórico e cultural. Investir na infraestrutura\nturística e na capacitação de guias e empresários locais.\n● Agricultura e Pesca: Incentivar a modernização da agricultura e pesca na cidade,\ncom programas de assistência…\n\n---\n\n[EDUCAÇÃO]\n…io (como transporte público\npor exemplo), garantindo a direitos e deveres entre as partes.\nEducação: Educação de qualidade é a base para o desenvolvimento de uma sociedade\nmais justa e próspera. Propostas incluem:\n● Valorização dos Profes…\n\n---\n\n[EMPREGO E RENDA]\n…Implementar um programa de coleta seletiva em\ntoda a cidade, com a criação de cooperativas de reciclagem que gerem emprego e\nrenda para as comunidades locais.\n● Educação Ambiental: Criar campanhas de conscientização sobre a importância…\n\n---\n\n[TECNOLOGIA E INOVAÇÃO]\n…mento da Guarda Civil Municipal: Investir na capacitação contínua dos\nguardas municipais, equipando-os com tecnologias modernas de vigilância e\ncomunicação, como câmeras corporais e sistemas de monitoramento em tempo real.\n● Centro de Coman…\n\n---\n\n[SAÚDE]\n…egional de crescimento e desenvolvimento.\n1. Bem-Estar e Desenvolvimento Social\nSaúde: Magé precisa de um sistema de saúde que seja acessível a todos os cidadãos,\ngarantindo atendimento de qualidade e humanizado. Propostas específicas…\n\n---\n\n[LGBTQIA+]\n…e adaptações nos processos\nseletivos e na infraestrutura de trabalho. Além disso, serão promovidas\npolíticas de inclusão que incentivem a diversidade dentro do serviço\npúblico municipal.\nImpacto Esperado: A realização de concursos públicos r…\n\n---\n\n[SANEAMENTO BÁSICO]\n…ão - Solicitar por todos os meios possíveis, a revisão do contrato entre\nmunicípio e a empresa responsável pelo saneamento e distribuição da água no\nmunicípio. Buscando assim a possível a municipalização destas áreas.\n● Conexões - Elaborar…\n\n---\n\n[PESSOA COM DEFICIÊNCIA]\n…o Social no Serviço Público: Garantir que os concursos públicos\nsejam acessíveis a todos os segmentos da população, incluindo\npessoas com deficiência, através de adaptações nos processos\nseletivos e na infraestrutura de trabalho. Além disso,…\n\n---\n\n[CRIANÇA E ADOLESCENTE]\n…scar recursos federais para a construção do Hospital da\nmulher em Surui.\nS\n● Saúde das crianças - Hospital Pediátrico na unidade já existente e atualmente sem\nuso, no hospital Dr Walter Arruda em Santo Aleixo.\n● Casa do autista - Buscar…\n\n---\n\n[MEIO AMBIENTE]\n…entrada e saída, além de\nimplementar programas de segurança voltados para estudantes e professores.\n3. Gestão Ambiental Integrada\nA preservação ambiental é crucial para garantir a qualidade de vida das gerações futuras.\nPropostas incluem:…\n\n---\n\n[SEGURANÇA ALIMENTAR]\n…m uma unidade\nvoltada a causa, na construção desse espaço referência em Magé.\n● Mulher - Fomentar a inclusão feminina nos postos de trabalho com programas\nespeciais de capacitação e reserva de vagas na indústria e comércio. E combater…\n\n---\n\n[MULHER]\n…o, com especial atenção à\nprevenção e tratamento de depressão e ansiedade.\n● Saúde da mulher - Buscar recursos federais para a construção do Hospital da\nmulher em Surui.\nS\n● Saúde das crianças - Hospital Pediátrico na unidade já existen…\n\n---\n\n[REGULARIZAÇÃO FUNDIÁRIA]\n…rbano de Magé deve ser planejado de forma sustentável, com foco na\nqualidade de vida dos cidadãos. Propostas incluem:\n● Regularização Fundiária: Implementar um programa de regularização fundiária,\ngarantindo que todas as famílias mageenses tenham a poss…\n\n---\n\n[CULTURA, ESPORTE E LAZER]\n…m laboratórios de informática, bibliotecas atualizadas, e\nespaços para práticas esportivas e culturais.\n● Climatização: Energia Solar em todo prédio público, principalmente nas unidades\neducacionais, encerrando assim,,qualquer desculpa e…\n\n---\n\n[FINANÇAS PÚBLICAS]\n…a total, com\na publicação online de todos os gastos públicos e a realização de audiências\npúblicas regulares para discutir o orçamento municipal e as prioridades de\ninvestimento.\n● Capacitação dos Servidores: Desenvolver programas de capac…\n\n---\n\n[ENERGIA E ILUMINAÇÃO]\n…ica, bibliotecas atualizadas, e\nespaços para práticas esportivas e culturais.\n● Climatização: Energia Solar em todo prédio público, principalmente nas unidades\neducacionais, encerrando assim,,qualquer desculpa e dependência de acordos com\na em…\n\n---\n\n[SEGURANÇA PÚBLICA]\n…a cidade\nde Magé em um modelo de desenvolvimento sustentável, bem-estar social, segurança e\ninovação. Davi Souza e Eliana Rodrigues, com vasta experiência e compromisso com a\ncidade, apresentam um conjunto de propostas para o mandato de 20…","themes":["transporte e mobilidade","turismo","saúde mental","saúde","LGBTQIA+","cultura, esporte e lazer","criança e adolescente","educação","transparência e ética","energia e iluminação","segurança pública","habitação","assistência social","regularização fundiária","emprego e renda","pessoa com deficiência","infraestrutura","saneamento básico","segurança alimentar","finanças públicas","gestão pública","tecnologia e inovação","meio ambiente","agricultura e rural","idoso","combate às drogas","mulher"]}