{"id":"260002273152","nome":"ALINE VASCONCELOS","partido":"REPUBLICANOS","municipio":"POÇO REDONDO","uf":"SE","text":"[INFRAESTRUTURA]\n…equipar e ampliar as cantinas escolares do Município;\n Ampliar e construir Creches e Escolas de Educação Infantil com a\ninfraestrutura modernizada, com a ampliação da instalação de ar-\ncondicionado em todas as salas de aula das escolas munici…\n\n---\n\n[RACISMO E IGUALDADE RACIAL]\n…erviços;\n Ampliações do espaço e melhorias dos serviços ofertados pelo CRAS\n(Centro Referência da Assistência Social) da Sede do Município e o Cras\nquilombola, assim como colocar em funcionamento o CRAS do Povoado\nSítios Novos;\n Fomentar…\n\n---\n\n[TURISMO]\n…es coletores de lixo;\n Ampliação nos planejamentos estratégicos para manutenção e\nconservação dos prédios públicos;\n Criação de uma central de atendimento presencial e online para receber as\ndemandas da população.\n11. TURISMO E CULTURA…\n\n---\n\n[ASSISTÊNCIA SOCIAL]\n…das as secretarias e áreas de atuação, estará disponível em cada\nlocalidade, oferecendo atendimento e serviços essenciais, como saúde,\neducação, assistência social, infraestrutura, entre outros. Esse projeto tem\ncomo objetivo aproximar a gestão púb…\n\n---\n\n[TRANSPORTE E MOBILIDADE]\n…as a\nexames oftalmológicos, diabéticos, ginecológicos e urológicos;\n Manutenção e aumento da quantidade de transportes para locomoção de\npacientes que necessitam de tratamento especializado em Aracaju;\n Ampliação e contratação de serviços…\n\n---\n\n[IDOSO]\n…afins, que podem oferecer atendimentos supervisionados à\npopulação.\n Desenvolver um programa voltado para a saúde do idoso, com atividades\nfísicas, acompanhamento médico regular e ações preventivas para\nmelhorar a qualidade de vida d…\n\n---\n\n[SAÚDE MENTAL]\n…equipes de saúde bucal nos Povoados: Areias, Flor da\nSerra e Bonsucesso;\n Implantação do CAPS e ambulatório de saúde metal municipal, bem\ncomo aumentar o número de profissionais para a realização de\natendimentos e acolhimentos psicol…\n\n---\n\n[TRANSPARÊNCIA E ÉTICA]\n…o Redondo e no\nbem-estar de sua população. Comprometemo-nos a adotar princípios de\ntransparência, participação cidadã e respeito às necessidades da população.\nEnfatizamos a relevância dos Conselhos Municipais como espaços fundamentais\npara o d…\n\n---\n\n[HABITAÇÃO]\n…as com treinos e preparatórios com o programa\n“Academia popular”.\n Manutenção e ampliação do programa “Melhor em Casa”, com equipes de\nsaúde visitando as famílias regularmente, garantindo acompanhamento e\norientações de saúde.\n Dese…\n\n---\n\n[GESTÃO PÚBLICA]\n…es de mobilidade e acessibilidade no ambiente escolar,\ncumprindo a legislação brasileira;\n4. ASSISTÊNCIA E INCLUSÃO SOCIAL\n Implantar o Projeto Gestão Itinerante, que levará os serviços da\nadministração municipal às comunidades mais di…\n\n---\n\n[COMBATE ÀS DROGAS]\n…ológicos;\n Manutenção e aumento da quantidade de transportes para locomoção de\npacientes que necessitam de tratamento especializado em Aracaju;\n Ampliação e contratação de serviços especializados: ginecologia,\npediatria, cirurgião geral,…\n\n---\n\n[AGRICULTURA E RURAL]\n…efeito Municipal no Povoado Sítios\nNovos;\n Extensão do gabinete do Prefeito Municipal para atendimento da\npopulação nos Povoados Santa Rosa do Ermírio e Sítios Novos.\n6. AGRICULTURA\n Implantação da feira de agricultura familiar com estrutu…\n\n---\n\n[EDUCAÇÃO]\n…m aquisição de novos equipamentos\ntecnológicos e qualificação profissional;\n Criação do NEP (núcleo de educação permanente), para realização de\natividades educativas e capacitação dos profissionais da Secretaria\nMunicipal de Saúde.\n For…\n\n---\n\n[EMPREGO E RENDA]\n…sos, e atendimentos psicológicos;\n Desenvolvimento de políticas públicas que visem à erradicação do\nanalfabetismo juvenil;\n Criação programas de educação profissional, geração de emprego e renda\npara os jovens;\n Criar um Fundo Municip…\n\n---\n\n[TECNOLOGIA E INOVAÇÃO]\n…dade interessada, com o objetivo de desenvolver\nhabilidades digitais essenciais, especialmente em áreas rurais com\nmenos acesso à tecnologia;\n Montar uma biblioteca móvel que percorra as escolas da rede,\nincentivando a leitura com a dispon…\n\n---\n\n[SAÚDE]\n…município onde todos tenham iguais oportunidades e possam viver com\ndignidade.\n2. SAÚDE\n Ampliar e melhorar o atendimento nas Farmácias Básicas garantindo a\ndistribuição de medicamentos gratuitamente;\n Construção de uma UNIDADE BÁSI…\n\n---\n\n[LGBTQIA+]\n…nselho Quilombola para a defesa e implantação de\nprojetos inclusivos para a comunidade negra;\n Abertura do Conselho e Centro de Referência em Direitos Humanos\nLGBTQIAPN+ de Poço Redondo;\n Melhoramento e ampliação dos serviços ofertados…\n\n---\n\n[SANEAMENTO BÁSICO]\n…ento médico regular e ações preventivas para\nmelhorar a qualidade de vida da terceira idade.\n Investir em melhorias no saneamento básico em todas as áreas do\nmunicípio, garantindo acesso a água potável, coleta e tratamento de\nesgoto, reduz…\n\n---\n\n[PESSOA COM DEFICIÊNCIA]\n…e Atendimento\nEducacional Especializado (CAEE), que é destinado á crianças e\njovens matriculados nas redes municipais de ensino portadores de\ndeficiências, com acompanhamento de profissionais especializados\n(Psicólogo Assistente Social, Peda…\n\n---\n\n[CRIANÇA E ADOLESCENTE]\n…des econômicas urbanas;\n Continuidade, ampliação e melhoramento do Centro de Atendimento\nEducacional Especializado (CAEE), que é destinado á crianças e\njovens matriculados nas redes municipais de ensino portadores de\ndeficiências, com a…\n\n---\n\n[MEIO AMBIENTE]\n…scriminação\ne violência contra as jovens mulheres;\n Incentivar através de bolsa com valor simbólico, jovens que não\nconcluíram o ensino fundamental, para que conclua.\n8. PRESERVAÇÃO DO MEIO AMBIENTE:\n Incentivar o reflorestamento nas nascent…\n\n---\n\n[SEGURANÇA ALIMENTAR]\n…tro Referência da Assistência Social) da Sede do Município e o Cras\nquilombola, assim como colocar em funcionamento o CRAS do Povoado\nSítios Novos;\n Fomentar a geração de renda fortalecendo o Associativismo,\nCooperativismo nas ativid…\n\n---\n\n[MULHER]\n…lhimentos psicológicos;\n Criação e ampliação de programas específicos voltados à saúde da\nmulher, incluindo a realização de exames preventivos (como mamografia\ne Papanicolau), apoio à saúde reprodutiva e planejamento familiar, além\nde…\n\n---\n\n[CULTURA, ESPORTE E LAZER]\n…visão de\nprofessores. Isso pode reforçar o aprendizado e fortalecer o senso de\ncolaboração entre os estudantes;\n Desenvolver o projeto “Cultura na Escola” que explore a história e a\ncultura do município e da região, integrando essas tem…\n\n---\n\n[FINANÇAS PÚBLICAS]\n…antação do CAPS e ambulatório de saúde metal municipal, bem\ncomo aumentar o número de profissionais para a realização de\natendimentos e acolhimentos psicológicos;\n Criação e ampliação de programas específicos voltados à saúde da\nmul…\n\n---\n\n[ENERGIA E ILUMINAÇÃO]\n…OBRAS E SERVIÇOS MUNICIPAIS\n Expansão, melhoria e modernização da iluminação pública, com a\ninstalação de iluminação de LED nas principais avenidas da sede e\nPovoados Santa Rosa e Sítios Novos;\n Instalação de energia solar nos prédios públi…\n\n---\n\n[SEGURANÇA PÚBLICA]\n…e incentivar os jovens no resgate da memória e o resgate dos\nvalores culturais e históricos do município;\n Criar projetos destinados ao combate a todas as práticas de discriminação\ne violência contra as jovens mulheres;\n Incentivar atra…","themes":["transporte e mobilidade","turismo","saúde mental","saúde","LGBTQIA+","cultura, esporte e lazer","criança e adolescente","educação","transparência e ética","energia e iluminação","segurança pública","habitação","assistência social","racismo e igualdade racial","emprego e renda","pessoa com deficiência","infraestrutura","saneamento básico","segurança alimentar","finanças públicas","gestão pública","tecnologia e inovação","meio ambiente","agricultura e rural","idoso","combate às drogas","mulher"]}