{"id":"50002170836","nome":"SERGINHO","partido":"AVANTE","municipio":"MUNDO NOVO","uf":"BA","text":"[INFRAESTRUTURA]\n…sistência Social\nEixo V – Agricultura, Pecuária e Desenvolvimento Econômico\nEixo VI – Infraestrutura e Serviços Públicos\nEixo VII – Meio Ambiente e Proteção Animal\nEixo VIII – Apoio à Mulher\n2\nUm dos maiores desafios e alegrias da minha vida fo…\n\n---\n\n[RACISMO E IGUALDADE RACIAL]\n…;\n• Discutir e elaborar plano de ação voltado ao combate à violência conta a mulher;\n• Discutir e elaborar políticas públicas de inclusão da pessoa com deficiência;\n• Discutir e elaborar políticas públicas de combate ao racismo, homofobi…\n\n---\n\n[TURISMO]\n…stração e gestão\nEixo II – Saúde e qualidade de vida\nEixo III – Educação, cultura, turismo, desporto e lazer\nEixo IV – Assistência Social\nEixo V – Agricultura, Pecuária e Desenvolvimento Econômico\nEixo VI – Infraestrutura e Serviços Públ…\n\n---\n\n[ASSISTÊNCIA SOCIAL]\n…qualidade de vida\nEixo III – Educação, cultura, turismo, desporto e lazer\nEixo IV – Assistência Social\nEixo V – Agricultura, Pecuária e Desenvolvimento Econômico\nEixo VI – Infraestrutura e Serviços Públicos\nEixo VII – Meio Ambiente e Proteção Anima…\n\n---\n\n[TRANSPORTE E MOBILIDADE]\n…organograma da Prefeitura Municipal e suas respectivas secretarias;\n• Criação do Departamento de Transportes;\n• Elaboração do Plano de Cargos, Carreiras e Vencimentos dos Servidores Efetivos;\n• Redimensionamento dos Cargos Comissionados co…\n\n---\n\n[IDOSO]\n…e capacitação técnica integral;\n• Estimular prática de atividade física, com profissional habilitado, para adolescentes e idosos\nem espaços públicos do município;\n• Manter e otimizar serviço para TFD;\n• Construção de UBS “Novo Horizon…\n\n---\n\n[SAÚDE MENTAL]\n…e de saúde municipal sobre saúde\nmental para melhoria do acolhimento e detecção precoce de transtornos mentais;\n• Garantir a Assistência Farmacêutica à Saúde Mental;\n• Ampliar a cobertura da Saúde Bucal no município;\n• Licenciar os estabeleci…\n\n---\n\n[TRANSPARÊNCIA E ÉTICA]\n…consonância com a valores que julgamos essenciais ao nosso\ngoverno, que são: moralidade, transparência, impessoalidade, trabalho, eficiência, e acima de\ntudo, RESPONSABILIDADE com o cidadão mundonovense.\n4\nEIXO I - ADMINISTRAÇÃO E GESTÃO\nBusc…\n\n---\n\n[HABITAÇÃO]\n….\nAÇÕES:\n• Continuidade no apoio as iniciativas e a estruturação dos Conselhos Municipais: da\nAssistência Social, dos Direitos da Criança e do Adolescente, dos Direitos do idoso, da\nPessoa com Deficiência, da Habitação, da Mulher, da Segur…\n\n---\n\n[GESTÃO PÚBLICA]\n…SUMÁRIO\nApresentação\nIntrodução\nEixo I – Administração e gestão\nEixo II – Saúde e qualidade de vida\nEixo III – Educação, cultura, turismo, desporto e lazer\nEixo IV – Assistência Social\nEixo V – Agricultura, Pecuá…\n\n---\n\n[COMBATE ÀS DROGAS]\n…ujeitos a VISA;\n• Implantação de doze salas de teleatendimento nas UBS;\n• Ampliação do Programa de Saúde do Trabalhador;\n• Criação de Programa de Combate às Drogas.\n8\nEIXO III - EDUCAÇÃO, CULTURA, DESPORTO E TURISMO\nEDUCAÇÃO\nOBJETIVO:\nE…\n\n---\n\n[AGRICULTURA E RURAL]\n…– Educação, cultura, turismo, desporto e lazer\nEixo IV – Assistência Social\nEixo V – Agricultura, Pecuária e Desenvolvimento Econômico\nEixo VI – Infraestrutura e Serviços Públicos\nEixo VII – Meio Ambiente e Proteção Animal\nEixo VIII – Apoio…\n\n---\n\n[EDUCAÇÃO]\n…ção\nEixo I – Administração e gestão\nEixo II – Saúde e qualidade de vida\nEixo III – Educação, cultura, turismo, desporto e lazer\nEixo IV – Assistência Social\nEixo V – Agricultura, Pecuária e Desenvolvimento Econômico\nEixo VI – Infraestrutu…\n\n---\n\n[EMPREGO E RENDA]\n…potencial como um dos principais\nimpulsionadores de desenvolvimento visando a criação de emprego e renda. Como instrumento\nprincipal para viabilizar este setor que é mola propulsora da nossa terra, faz-se necessário a\nintensificação do…\n\n---\n\n[TECNOLOGIA E INOVAÇÃO]\n…los e linhas;\n• Manutenção e ampliação do Projeto AABB COMUNIDADE;\n• Continuidade dos investimentos em materiais pedagógicos, na melhoria da qualidade da\nmerenda, tecnologia da informação e na manutenção, ampliação e modernização dos\nespaço…\n\n---\n\n[SAÚDE]\n…SUMÁRIO\nApresentação\nIntrodução\nEixo I – Administração e gestão\nEixo II – Saúde e qualidade de vida\nEixo III – Educação, cultura, turismo, desporto e lazer\nEixo IV – Assistência Social\nEixo V – Agricultura, Pecuária e Desenvolv…\n\n---\n\n[LGBTQIA+]\n…tir e elaborar plano de ação voltado ao combate à violência conta a mulher;\n• Discutir e elaborar políticas públicas de inclusão da pessoa com deficiência;\n• Discutir e elaborar políticas públicas de combate ao racismo, homofobia e à intol…\n\n---\n\n[SANEAMENTO BÁSICO]\n…ionais, seguindo as exigências do programa de Habitação\n12\nde Interesse Social que respondam a demanda da zona rural e urbana, e às políticas nacional\ne municipal de habitação;\n• Buscar recursos para implantar Programas de saneamento básico…\n\n---\n\n[PESSOA COM DEFICIÊNCIA]\n…sistência social.\nAÇÕES:\n• Continuidade no apoio as iniciativas e a estruturação dos Conselhos Municipais: da\nAssistência Social, dos Direitos da Criança e do Adolescente, dos Direitos do idoso, da\nPessoa com Deficiência, da Habitação, da Mu…\n\n---\n\n[CRIANÇA E ADOLESCENTE]\n…plantar uma sala de recurso multifuncional e garantir a formação continuada dos\nprofessores ao atendimento educacional especializado;\n9\n• Estimular e incentivar o acesso das crianças de 3 a 5 anos de idade na educação infantil;\n• Fortale…\n\n---\n\n[MEIO AMBIENTE]\n…ia e Desenvolvimento Econômico\nEixo VI – Infraestrutura e Serviços Públicos\nEixo VII – Meio Ambiente e Proteção Animal\nEixo VIII – Apoio à Mulher\n2\nUm dos maiores desafios e alegrias da minha vida foi receber o convite para ser candidato a\npre…\n\n---\n\n[SEGURANÇA ALIMENTAR]\n…o apoio as iniciativas e a estruturação dos Conselhos Municipais: da\nAssistência Social, dos Direitos da Criança e do Adolescente, dos Direitos do idoso, da\nPessoa com Deficiência, da Habitação, da Mulher, da Segurança Alimentar e Nutricional;\n• Apo…\n\n---\n\n[MULHER]\n…tura e Serviços Públicos\nEixo VII – Meio Ambiente e Proteção Animal\nEixo VIII – Apoio à Mulher\n2\nUm dos maiores desafios e alegrias da minha vida foi receber o convite para ser candidato a\nprefeito de Mundo Novo, cidade onde nasci e esc…\n\n---\n\n[REGULARIZAÇÃO FUNDIÁRIA]\n…12\nde Interesse Social que respondam a demanda da zona rural e urbana, e às políticas nacional\ne municipal de habitação;\n• Buscar recursos para implantar Programas de saneamento básico;\n• Apoiar e implementar o processo de regularização fundiária das o…\n\n---\n\n[CULTURA, ESPORTE E LAZER]\n…– Administração e gestão\nEixo II – Saúde e qualidade de vida\nEixo III – Educação, cultura, turismo, desporto e lazer\nEixo IV – Assistência Social\nEixo V – Agricultura, Pecuária e Desenvolvimento Econômico\nEixo VI – Infraestrutura e Serv…\n\n---\n\n[FINANÇAS PÚBLICAS]\n…ças à democracia,\ndegradação do ambiente político e da representação popular, crise nas finanças públicas... estes\ne outros fatores foram preponderantes na minha decisão de disputar o pleito de 2024, como\ncandidato a Prefeito, visando con…\n\n---\n\n[SEGURANÇA PÚBLICA]\n…o apoio as iniciativas e a estruturação dos Conselhos Municipais: da\nAssistência Social, dos Direitos da Criança e do Adolescente, dos Direitos do idoso, da\nPessoa com Deficiência, da Habitação, da Mulher, da Segurança Alimentar e Nutricio…","themes":["transporte e mobilidade","turismo","saúde mental","saúde","LGBTQIA+","cultura, esporte e lazer","criança e adolescente","educação","transparência e ética","segurança pública","habitação","assistência social","regularização fundiária","racismo e igualdade racial","emprego e renda","pessoa com deficiência","infraestrutura","saneamento básico","segurança alimentar","finanças públicas","gestão pública","tecnologia e inovação","meio ambiente","agricultura e rural","idoso","combate às drogas","mulher"]}