{"id":"90002252619","nome":"CLÁUDIO CAIXETA","partido":"PDT","municipio":"INACIOLÂNDIA","uf":"GO","text":"[INFRAESTRUTURA]\n…ar a realização de bailes e festas para a melhor idade.\nOBRAS E URBANISMO\nRecapear o asfalto das ruas que necessitarem de correção. Continuar a fazer calcadas e\nmeios fios na cidade para melhorar o ambiente e diminuir a sujeira.\nAdquirir…\n\n---\n\n[ASSISTÊNCIA SOCIAL]\n…ortantes companheiros de trabalho. Temos como princípios os valores em favor\nda família e do cidadão, honestidade, trabalho, respeito, transparência e paixão pela\nnossa cidade e pelas pessoas que aqui vivem, a estes, os nossos compromiss…\n\n---\n\n[TRANSPORTE E MOBILIDADE]\n…ENÇÃO ÀS CARIES em todos os\nseguimentos da comunidade.\nAssegurar atendimento com transporte e apoio as pessoas que necessitam de\ntratamento em outo município.\nFirmar convenio para melhor atender as mulheres na prevenção de câncer de mama,\na…\n\n---\n\n[TRANSPARÊNCIA E ÉTICA]\n…s os valores em favor\nda família e do cidadão, honestidade, trabalho, respeito, transparência e paixão pela\nnossa cidade e pelas pessoas que aqui vivem, a estes, os nossos compromissos\npessoais. Nele tivemos a preocupação de detalhar os progra…\n\n---\n\n[HABITAÇÃO]\n…convênio com o Governo de Estado, para atender pessoas carentes, com\nmelhorias nas moradias, como reforma e ampliação.\nDar atenção especial ao programa Recomeço e ampliar a horta comunitária\nRealizar campanha do agasalho para atender as…\n\n---\n\n[GESTÃO PÚBLICA]\n…de apresentar ao nosso querido povo de Inaciolândia o PLANO\nDE GOVERNO, para a gestão de 2025-2028, este documento que estabelece as\ndiretrizes e as medidas que serão tomadas no novo governo. apresenta as principais\npropostas do candid…\n\n---\n\n[COMBATE ÀS DROGAS]\n…idade.\nAssegurar atendimento com transporte e apoio as pessoas que necessitam de\ntratamento em outo município.\nFirmar convenio para melhor atender as mulheres na prevenção de câncer de mama,\natravés de mamografia indicada para mulheres acim…\n\n---\n\n[AGRICULTURA E RURAL]\n…ormas no Cemitério local.\nManutenção das praças do município limpas e em bom estado.\nAGRICULTURA\nCriar programas de recuperação de pontes, aterros e mata-burros na zona rural, e\nfazendo as manutenções necessárias.\nManter funcionário e veicul…\n\n---\n\n[EDUCAÇÃO]\n…hão caçamba em convenio com o governo federal.\nTransporte e apoio aos programas da educação, visitas culturais em outras regiões.\nDisponibilizar trator e grade aos pequenos produtores rurais.\nCIDADANIA E PROMOÇÃO SOCIAL\nCadastrar as famíl…\n\n---\n\n[EMPREGO E RENDA]\n…OMOÇÃO SOCIAL\nCadastrar as famílias em condições de risco por motivo de doença, desemprego,\nisolamento de familiares, garantindo acompanhamento por assistente social,\npsicóloga e doações de cestas básicas, remédios e agasalhos.\nOferecer…\n\n---\n\n[SAÚDE]\n…de ANIVERSÁRIO DA CIDADE. Apoio às\nmanifestações artísticas e festas culturais.\nSAÚDE\nMuito será feito para melhorar a saúde preventiva e curativa do nosso povo, dentre\neles:\nMelhorar o atendimento humanizado onde os pacientes serão b…\n\n---\n\n[SANEAMENTO BÁSICO]\n…empregos para a população.\nFazer gestão ao Governo Federal para ampliação da rede de esgoto.\nPoda de arvores em órgãos públicos, evitando acidentes, falta de energia, evitando\npontos escuros a noite\nRevitalização do pátio da prefeitura…\n\n---\n\n[PESSOA COM DEFICIÊNCIA]\n…trução de Casas\nPopulares.\nManter o convênio com o Governo Federal para cadastro e inclusão das famílias no\nprograma Bolsa Família.\nFazer convênio com o Governo de Estado, para atender pessoas carentes, com\nmelhorias nas moradias, como re…\n\n---\n\n[CRIANÇA E ADOLESCENTE]\n…oações de cestas básicas, remédios e agasalhos.\nOferecer lazer e distração para as crianças do nosso município nas datas especiais\ncomo Páscoa, Dia das crianças e Natal.\nManter o PROGRAMA Serviço de Convivência e Fortalecimento de Víncul…\n\n---\n\n[MEIO AMBIENTE]\n…olícia civil para manter o escritório local.\nMonitoramento de segurança no município\nMEIO AMBIENTE\nProjeto de repovoamento do rio dos bois em nosso município. Criar o Conselho\nMunicipal de Meio Ambiente.\nRecolher 100% do lixo produzido na cida…\n\n---\n\n[SEGURANÇA ALIMENTAR]\n…s, como reforma e ampliação.\nDar atenção especial ao programa Recomeço e ampliar a horta comunitária\nRealizar campanha do agasalho para atender as famílias carentes.\nAuxiliar as famílias carentes com entrega de kits para gestantes.\nAux…\n\n---\n\n[MULHER]\n…cializados no município sua sede\nprópria.\nFirmar convenio para melhor atender as mulheres na prevenção de câncer de mama,\natravés de mamografia indicada para mulheres acima de 40 anos.\nDesenvolver programa permanente de PREVENÇÃO ÀS CAR…\n\n---\n\n[REGULARIZAÇÃO FUNDIÁRIA]\n…RURAL, trazendo cursos\nprofissionalizantes para o setor.\nRecolhimento de entulho em propriedades rurais.\nApoio no transporte de insumos ao pequeno produtor.\nSEGURANÇA PÚBLICA\nFortalecer o convênio com a Secretaria de Segurança Pública do Es…\n\n---\n\n[CULTURA, ESPORTE E LAZER]\n…ional festa de ANIVERSÁRIO DA CIDADE. Apoio às\nmanifestações artísticas e festas culturais.\nSAÚDE\nMuito será feito para melhorar a saúde preventiva e curativa do nosso povo, dentre\neles:\nMelhorar o atendimento humanizado onde os paciente…\n\n---\n\n[FINANÇAS PÚBLICAS]\n…xão pela\nnossa cidade e pelas pessoas que aqui vivem, a estes, os nossos compromissos\npessoais. Nele tivemos a preocupação de detalhar os programas e ações que iremos\nimplantar e executar na nossa gestão. Este plano traz diretrizes e…\n\n---\n\n[SEGURANÇA PÚBLICA]\n…sição de material didático pedagógico para o ensino de educação\ninfantil.\nGarantir segurança nas unidades de ensino\nReformar e adequar as unidades de ensino para ofertar melhores condições de\natendimento aos educandos.\nInvestimento e adapt…","themes":["transporte e mobilidade","saúde","cultura, esporte e lazer","criança e adolescente","educação","transparência e ética","segurança pública","habitação","assistência social","regularização fundiária","pessoa com deficiência","infraestrutura","saneamento básico","segurança alimentar","finanças públicas","gestão pública","meio ambiente","mulher","agricultura e rural","emprego e renda","combate às drogas"]}